conexia/__init__.py
conexia/cache.py
conexia/cli.py
conexia/core.py
conexia/exceptions.py
conexia/utils.py
conexia/middleware/__init__.py
conexia/middleware/django.py
conexia/middleware/flask.py
conexia-0.2.0.dist-info/LICENSE
conexia-0.2.0.dist-info/METADATA
conexia-0.2.0.dist-info/WHEEL
conexia-0.2.0.dist-info/entry_points.txt
conexia-0.2.0.dist-info/top_level.txt
conexia-0.2.0.dist-info/RECORD
