Metadata-Version: 2.1
Name: conexia
Version: 0.2.0
Summary: A Python library for fetching real IP and Port using STUN servers and easily integratable with Python backend frameworks.
Home-page: https://github.com/paulsonlegacy/conexia
Author: Paulson Bosah
Author-email: paulsonbosah@gmail.com
License: UNKNOWN
Platform: UNKNOWN
Classifier: Programming Language :: Python :: 3
Classifier: License :: OSI Approved :: MIT License
Classifier: Operating System :: OS Independent
Requires-Python: >=3.7
License-File: LICENSE
Requires-Dist: pystun3>=2.0.0
Requires-Dist: cachetools>=5.5.1
Requires-Dist: redis>=5.1.0
Requires-Dist: pytz>=2024.1
